AUTHORS.rst
CHANGELOG.rst
CONTRIBUTING.rst
LICENSE.md
README.rst
coinflip/__init__.py
coinflip/__main__.py
coinflip/_randtests/__init__.py
coinflip/_randtests/common/collections.py
coinflip/_randtests/common/core.py
coinflip/_randtests/common/exceptions.py
coinflip/_randtests/common/pprint.py
coinflip/_randtests/common/result.py
coinflip/_randtests/common/testutils.py
coinflip/_randtests/common/typing.py
coinflip/_randtests/complexity.py
coinflip/_randtests/cusum.py
coinflip/_randtests/entropy.py
coinflip/_randtests/excursions.py
coinflip/_randtests/fourier.py
coinflip/_randtests/frequency.py
coinflip/_randtests/matrix.py
coinflip/_randtests/runs.py
coinflip/_randtests/serial.py
coinflip/_randtests/template.py
coinflip/_randtests/universal.py
coinflip/algorithms.py
coinflip/cli/__init__.py
coinflip/cli/commands.py
coinflip/cli/parsing.py
coinflip/cli/pprint.py
coinflip/cli/report.py
coinflip/cli/runner.py
coinflip/collections.py
coinflip/generators.py
coinflip/randtests.py
coinflip/randtests_refimpl.py
coinflip-0.1.5.dist-info/entry_points.txt
coinflip-0.1.5.dist-info/LICENSE.md
coinflip-0.1.5.dist-info/WHEEL
coinflip-0.1.5.dist-info/METADATA
coinflip-0.1.5.dist-info/RECORD
