Metadata-Version: 2.1
Name: coinflip
Version: 0.1.5
Summary: Randomness testing for humans
Home-page: https://github.com/Honno/coinflip
License: BSD-3-Clause
Keywords: rng,nist,rngtest,randomness,randomness-testing
Author: Matthew Barber
Author-email: quitesimplymatt@gmail.com
Requires-Python: >=3.7,<4.0
Classifier: Development Status :: 4 - Beta
Classifier: Environment :: Console
Classifier: Intended Audience :: Developers
Classifier: Intended Audience :: Education
Classifier: Intended Audience :: End Users/Desktop
Classifier: License :: OSI Approved :: BSD License
Classifier: Operating System :: MacOS
Classifier: Operating System :: Microsoft :: Windows
Classifier: Operating System :: POSIX
Classifier: Operating System :: Unix
Classifier: Programming Language :: Python
Classifier: Programming Language :: Python :: 3
Classifier: Programming Language :: Python :: 3.7
Classifier: Programming Language :: Python :: 3.8
Classifier: Programming Language :: Python :: 3.9
Classifier: Programming Language :: Python :: Implementation :: CPython
Classifier: Topic :: Security :: Cryptography
Classifier: Topic :: Software Development :: Libraries
Classifier: Topic :: Utilities
Provides-Extra: docs
Provides-Extra: refimpl
Provides-Extra: test
Requires-Dist: Jinja2 (>=2.11.2,<3.0.0)
Requires-Dist: altair (>=4.1.0,<5.0.0)
Requires-Dist: click (>=7.1.2,<8.0.0)
Requires-Dist: defaultlist (>=1.0.0,<2.0.0); extra == "test"
Requires-Dist: hypothesis (>=5.41.2,<6.0.0); extra == "test"
Requires-Dist: more-itertools (>=8.6.0,<9.0.0); extra == "refimpl"
Requires-Dist: numpy (>=1.19.4,<2.0.0)
Requires-Dist: pandas (>=1.1.4,<2.0.0)
Requires-Dist: pytest (>=6.1.2,<7.0.0); extra == "test"
Requires-Dist: pytest-timeout (>=1.4.2,<2.0.0); extra == "test"
Requires-Dist: rich (>=9.2.0,<10.0.0)
Requires-Dist: scipy (>=1.5.4,<2.0.0)
Requires-Dist: sortedcontainers (>=2.3.0,<3.0.0)
Requires-Dist: sphinx (>=3,<4); extra == "docs"
Requires-Dist: sphinx-click (>=2.5.0,<3.0.0); extra == "docs"
Requires-Dist: sphinx-rtd-theme (>=0.5.0,<0.6.0); extra == "docs"
Requires-Dist: tox (>=3.20.1,<4.0.0); extra == "test"
Requires-Dist: typing-extensions (>=3.7.4,<4.0.0)
Project-URL: Documentation, https://coinflip.readthedocs.io/
Project-URL: Repository, https://github.com/Honno/coinflip
